EgyVoc/__init__.py
EgyVoc/parserData/__init__.py
EgyVoc/parserData/copticSahidic_1_0/__init__.py
EgyVoc/parserData/dependencies/__init__.py
EgyVoc/parserData/dependencies/FAAL_jar/FAAL_jar_Global.jar
EgyVoc/parserData/dependencies/FAAL_jar/__init__.py
EgyVoc/parserData/dependencies/FAAL_jar/config/__init__.py
EgyVoc/parserData/dependencies/FAAL_jar/config/external_corr_glob_sim_score_function.txt
EgyVoc/parserData/dependencies/FAAL_jar/config/features_coarticulation.txt
EgyVoc/parserData/dependencies/FAAL_jar/config/features_diphthongs.txt
EgyVoc/parserData/dependencies/FAAL_jar/config/phon_categories.txt
EgyVoc/parserData/dependencies/FAAL_jar/config/phon_diacritics.txt
EgyVoc/parserData/dependencies/FAAL_jar/config/phon_features.txt
EgyVoc/parserData/dependencies/FAAL_jar/config/saliences_to_use_matches_phon_categories.txt
EgyVoc/parserData/dependencies/FAAL_jar/config/saliences/__init__.py
EgyVoc/parserData/dependencies/FAAL_jar/config/saliences/salience_cat_1.txt
EgyVoc/parserData/dependencies/FAAL_jar/config/saliences/salience_cat_2.txt
EgyVoc/parserData/dependencies/FAAL_jar/config/saliences/salience_cat_3.txt
EgyVoc/parserData/dependencies/interfaceFAAL/__init__.py
EgyVoc/parserData/dependencies/multiMatch/__init__.py
EgyVoc/parserData/groupWritingCombined/__init__.py
EgyVoc/parserData/groupWritingPeriod1/__init__.py
EgyVoc/parserData/groupWritingPeriod2/__init__.py
EgyVoc/parserData/groupWritingPeriod3/__init__.py
EgyVoc/parserData/groupWritingPeriod4/__init__.py
EgyVoc/parserData/joinReconstructions/__init__.py
EgyVoc/parserData/parserProtoCoptic/__init__.py
EgyVoc-0.0.11.dist-info/LICENCE
EgyVoc-0.0.11.dist-info/METADATA
EgyVoc-0.0.11.dist-info/WHEEL
EgyVoc-0.0.11.dist-info/top_level.txt
EgyVoc-0.0.11.dist-info/RECORD
