Metadata-Version: 2.1
Name: EgyVoc
Version: 0.0.11
Summary: Vocalizer for Ancient Egyptian
Home-page: https://github.com/MKilani/EgyVoc
Author: Marwan Kilani
Author-email: kilani.edu@gmail.com
License: UNKNOWN
Platform: UNKNOWN
Classifier: Programming Language :: Python :: 3
Classifier: License :: OSI Approved :: MIT License
Classifier: Operating System :: OS Independent
Requires-Python: >=3.0
Requires-Dist: py4j
